<annotation>
	<folder>Dataset</folder>
	<filename>F3DW1M99VQ.jpg</filename>
	<path>C:\Users\papommie\Documents\POC\Total\Pictures for OCR\Dataset\IMG_1669.JPG</path>
	<source>
		<database>Unknown</database>
	</source>
	<size>
		<width>4032</width>
		<height>3024</height>
		<depth>3</depth>
	</size>
	<segmented>0</segmented>
	<object>
		<name>character</name>
		<pose>Unspecified</pose>
		<truncated>0</truncated>
		<difficult>0</difficult>
		<bndbox>
			<xmin>1040</xmin>
			<ymin>2045</ymin>
			<xmax>1181</xmax>
			<ymax>2169</ymax>
		</bndbox>
	</object>
	<object>
		<name>character</name>
		<pose>Unspecified</pose>
		<truncated>0</truncated>
		<difficult>0</difficult>
		<bndbox>
			<xmin>1074</xmin>
			<ymin>1979</ymin>
			<xmax>1188</xmax>
			<ymax>2074</ymax>
		</bndbox>
	</object>
	<object>
		<name>character</name>
		<pose>Unspecified</pose>
		<truncated>0</truncated>
		<difficult>0</difficult>
		<bndbox>
			<xmin>1067</xmin>
			<ymin>1902</ymin>
			<xmax>1174</xmax>
			<ymax>1988</ymax>
		</bndbox>
	</object>
	<object>
		<name>character</name>
		<pose>Unspecified</pose>
		<truncated>0</truncated>
		<difficult>0</difficult>
		<bndbox>
			<xmin>1071</xmin>
			<ymin>1807</ymin>
			<xmax>1205</xmax>
			<ymax>1917</ymax>
		</bndbox>
	</object>
	<object>
		<name>character</name>
		<pose>Unspecified</pose>
		<truncated>0</truncated>
		<difficult>0</difficult>
		<bndbox>
			<xmin>1069</xmin>
			<ymin>1726</ymin>
			<xmax>1198</xmax>
			<ymax>1812</ymax>
		</bndbox>
	</object>
	<object>
		<name>character</name>
		<pose>Unspecified</pose>
		<truncated>0</truncated>
		<difficult>0</difficult>
		<bndbox>
			<xmin>1067</xmin>
			<ymin>1633</ymin>
			<xmax>1190</xmax>
			<ymax>1721</ymax>
		</bndbox>
	</object>
	<object>
		<name>character</name>
		<pose>Unspecified</pose>
		<truncated>0</truncated>
		<difficult>0</difficult>
		<bndbox>
			<xmin>1033</xmin>
			<ymin>1471</ymin>
			<xmax>1183</xmax>
			<ymax>1645</ymax>
		</bndbox>
	</object>
	<object>
		<name>character</name>
		<pose>Unspecified</pose>
		<truncated>0</truncated>
		<difficult>0</difficult>
		<bndbox>
			<xmin>1057</xmin>
			<ymin>1343</ymin>
			<xmax>1162</xmax>
			<ymax>1438</ymax>
		</bndbox>
	</object>
	<object>
		<name>character</name>
		<pose>Unspecified</pose>
		<truncated>0</truncated>
		<difficult>0</difficult>
		<bndbox>
			<xmin>1029</xmin>
			<ymin>1226</ymin>
			<xmax>1164</xmax>
			<ymax>1350</ymax>
		</bndbox>
	</object>
	<object>
		<name>character</name>
		<pose>Unspecified</pose>
		<truncated>0</truncated>
		<difficult>0</difficult>
		<bndbox>
			<xmin>1057</xmin>
			<ymin>940</ymin>
			<xmax>1169</xmax>
			<ymax>1050</ymax>
		</bndbox>
	</object>
	<object>
		<name>character</name>
		<pose>Unspecified</pose>
		<truncated>0</truncated>
		<difficult>0</difficult>
		<bndbox>
			<xmin>1071</xmin>
			<ymin>836</ymin>
			<xmax>1188</xmax>
			<ymax>931</ymax>
		</bndbox>
	</object>
	<object>
		<name>character</name>
		<pose>Unspecified</pose>
		<truncated>0</truncated>
		<difficult>0</difficult>
		<bndbox>
			<xmin>1076</xmin>
			<ymin>686</ymin>
			<xmax>1193</xmax>
			<ymax>824</ymax>
		</bndbox>
	</object>
	<object>
		<name>character</name>
		<pose>Unspecified</pose>
		<truncated>0</truncated>
		<difficult>0</difficult>
		<bndbox>
			<xmin>1274</xmin>
			<ymin>2086</ymin>
			<xmax>1393</xmax>
			<ymax>2145</ymax>
		</bndbox>
	</object>
	<object>
		<name>character</name>
		<pose>Unspecified</pose>
		<truncated>0</truncated>
		<difficult>0</difficult>
		<bndbox>
			<xmin>1262</xmin>
			<ymin>1993</ymin>
			<xmax>1400</xmax>
			<ymax>2081</ymax>
		</bndbox>
	</object>
	<object>
		<name>character</name>
		<pose>Unspecified</pose>
		<truncated>0</truncated>
		<difficult>0</difficult>
		<bndbox>
			<xmin>1274</xmin>
			<ymin>1890</ymin>
			<xmax>1402</xmax>
			<ymax>1990</ymax>
		</bndbox>
	</object>
	<object>
		<name>character</name>
		<pose>Unspecified</pose>
		<truncated>0</truncated>
		<difficult>0</difficult>
		<bndbox>
			<xmin>1283</xmin>
			<ymin>1805</ymin>
			<xmax>1395</xmax>
			<ymax>1876</ymax>
		</bndbox>
	</object>
	<object>
		<name>character</name>
		<pose>Unspecified</pose>
		<truncated>0</truncated>
		<difficult>0</difficult>
		<bndbox>
			<xmin>1255</xmin>
			<ymin>1655</ymin>
			<xmax>1371</xmax>
			<ymax>1781</ymax>
		</bndbox>
	</object>
	<object>
		<name>character</name>
		<pose>Unspecified</pose>
		<truncated>0</truncated>
		<difficult>0</difficult>
		<bndbox>
			<xmin>1252</xmin>
			<ymin>1569</ymin>
			<xmax>1371</xmax>
			<ymax>1662</ymax>
		</bndbox>
	</object>
	<object>
		<name>character</name>
		<pose>Unspecified</pose>
		<truncated>0</truncated>
		<difficult>0</difficult>
		<bndbox>
			<xmin>1252</xmin>
			<ymin>1510</ymin>
			<xmax>1364</xmax>
			<ymax>1571</ymax>
		</bndbox>
	</object>
	<object>
		<name>character</name>
		<pose>Unspecified</pose>
		<truncated>0</truncated>
		<difficult>0</difficult>
		<bndbox>
			<xmin>1260</xmin>
			<ymin>1374</ymin>
			<xmax>1388</xmax>
			<ymax>1493</ymax>
		</bndbox>
	</object>
	<object>
		<name>character</name>
		<pose>Unspecified</pose>
		<truncated>0</truncated>
		<difficult>0</difficult>
		<bndbox>
			<xmin>1229</xmin>
			<ymin>1210</ymin>
			<xmax>1360</xmax>
			<ymax>1343</ymax>
		</bndbox>
	</object>
	<object>
		<name>character</name>
		<pose>Unspecified</pose>
		<truncated>0</truncated>
		<difficult>0</difficult>
		<bndbox>
			<xmin>1467</xmin>
			<ymin>2012</ymin>
			<xmax>1586</xmax>
			<ymax>2143</ymax>
		</bndbox>
	</object>
	<object>
		<name>character</name>
		<pose>Unspecified</pose>
		<truncated>0</truncated>
		<difficult>0</difficult>
		<bndbox>
			<xmin>1483</xmin>
			<ymin>1917</ymin>
			<xmax>1598</xmax>
			<ymax>2038</ymax>
		</bndbox>
	</object>
	<object>
		<name>character</name>
		<pose>Unspecified</pose>
		<truncated>0</truncated>
		<difficult>0</difficult>
		<bndbox>
			<xmin>1450</xmin>
			<ymin>1774</ymin>
			<xmax>1586</xmax>
			<ymax>1929</ymax>
		</bndbox>
	</object>
	<object>
		<name>character</name>
		<pose>Unspecified</pose>
		<truncated>0</truncated>
		<difficult>0</difficult>
		<bndbox>
			<xmin>1445</xmin>
			<ymin>1674</ymin>
			<xmax>1574</xmax>
			<ymax>1783</ymax>
		</bndbox>
	</object>
	<object>
		<name>character</name>
		<pose>Unspecified</pose>
		<truncated>0</truncated>
		<difficult>0</difficult>
		<bndbox>
			<xmin>1450</xmin>
			<ymin>1602</ymin>
			<xmax>1588</xmax>
			<ymax>1702</ymax>
		</bndbox>
	</object>
	<object>
		<name>character</name>
		<pose>Unspecified</pose>
		<truncated>0</truncated>
		<difficult>0</difficult>
		<bndbox>
			<xmin>1433</xmin>
			<ymin>1512</ymin>
			<xmax>1562</xmax>
			<ymax>1614</ymax>
		</bndbox>
	</object>
	<object>
		<name>character</name>
		<pose>Unspecified</pose>
		<truncated>0</truncated>
		<difficult>0</difficult>
		<bndbox>
			<xmin>1436</xmin>
			<ymin>1371</ymin>
			<xmax>1552</xmax>
			<ymax>1479</ymax>
		</bndbox>
	</object>
	<object>
		<name>character</name>
		<pose>Unspecified</pose>
		<truncated>0</truncated>
		<difficult>0</difficult>
		<bndbox>
			<xmin>1436</xmin>
			<ymin>1314</ymin>
			<xmax>1550</xmax>
			<ymax>1410</ymax>
		</bndbox>
	</object>
	<object>
		<name>character</name>
		<pose>Unspecified</pose>
		<truncated>0</truncated>
		<difficult>0</difficult>
		<bndbox>
			<xmin>1443</xmin>
			<ymin>1243</ymin>
			<xmax>1550</xmax>
			<ymax>1314</ymax>
		</bndbox>
	</object>
	<object>
		<name>character</name>
		<pose>Unspecified</pose>
		<truncated>0</truncated>
		<difficult>0</difficult>
		<bndbox>
			<xmin>1440</xmin>
			<ymin>1183</ymin>
			<xmax>1543</xmax>
			<ymax>1238</ymax>
		</bndbox>
	</object>
	<object>
		<name>character</name>
		<pose>Unspecified</pose>
		<truncated>0</truncated>
		<difficult>0</difficult>
		<bndbox>
			<xmin>1417</xmin>
			<ymin>1017</ymin>
			<xmax>1538</xmax>
			<ymax>1117</ymax>
		</bndbox>
	</object>
	<object>
		<name>character</name>
		<pose>Unspecified</pose>
		<truncated>0</truncated>
		<difficult>0</difficult>
		<bndbox>
			<xmin>1417</xmin>
			<ymin>912</ymin>
			<xmax>1555</xmax>
			<ymax>1043</ymax>
		</bndbox>
	</object>
	<object>
		<name>character</name>
		<pose>Unspecified</pose>
		<truncated>0</truncated>
		<difficult>0</difficult>
		<bndbox>
			<xmin>1460</xmin>
			<ymin>805</ymin>
			<xmax>1579</xmax>
			<ymax>910</ymax>
		</bndbox>
	</object>
	<object>
		<name>character</name>
		<pose>Unspecified</pose>
		<truncated>0</truncated>
		<difficult>0</difficult>
		<bndbox>
			<xmin>1464</xmin>
			<ymin>719</ymin>
			<xmax>1583</xmax>
			<ymax>800</ymax>
		</bndbox>
	</object>
	<object>
		<name>character</name>
		<pose>Unspecified</pose>
		<truncated>0</truncated>
		<difficult>0</difficult>
		<bndbox>
			<xmin>1657</xmin>
			<ymin>2110</ymin>
			<xmax>1814</xmax>
			<ymax>2186</ymax>
		</bndbox>
	</object>
	<object>
		<name>character</name>
		<pose>Unspecified</pose>
		<truncated>0</truncated>
		<difficult>0</difficult>
		<bndbox>
			<xmin>1674</xmin>
			<ymin>2031</ymin>
			<xmax>1805</xmax>
			<ymax>2102</ymax>
		</bndbox>
	</object>
	<object>
		<name>character</name>
		<pose>Unspecified</pose>
		<truncated>0</truncated>
		<difficult>0</difficult>
		<bndbox>
			<xmin>1657</xmin>
			<ymin>1874</ymin>
			<xmax>1798</xmax>
			<ymax>2024</ymax>
		</bndbox>
	</object>
	<object>
		<name>character</name>
		<pose>Unspecified</pose>
		<truncated>0</truncated>
		<difficult>0</difficult>
		<bndbox>
			<xmin>1667</xmin>
			<ymin>1764</ymin>
			<xmax>1802</xmax>
			<ymax>1874</ymax>
		</bndbox>
	</object>
	<object>
		<name>character</name>
		<pose>Unspecified</pose>
		<truncated>0</truncated>
		<difficult>0</difficult>
		<bndbox>
			<xmin>1655</xmin>
			<ymin>1686</ymin>
			<xmax>1774</xmax>
			<ymax>1771</ymax>
		</bndbox>
	</object>
	<object>
		<name>character</name>
		<pose>Unspecified</pose>
		<truncated>0</truncated>
		<difficult>0</difficult>
		<bndbox>
			<xmin>1664</xmin>
			<ymin>1574</ymin>
			<xmax>1764</xmax>
			<ymax>1690</ymax>
		</bndbox>
	</object>
	<object>
		<name>character</name>
		<pose>Unspecified</pose>
		<truncated>0</truncated>
		<difficult>0</difficult>
		<bndbox>
			<xmin>1655</xmin>
			<ymin>1507</ymin>
			<xmax>1767</xmax>
			<ymax>1593</ymax>
		</bndbox>
	</object>
	<object>
		<name>character</name>
		<pose>Unspecified</pose>
		<truncated>0</truncated>
		<difficult>0</difficult>
		<bndbox>
			<xmin>1698</xmin>
			<ymin>1283</ymin>
			<xmax>1802</xmax>
			<ymax>1457</ymax>
		</bndbox>
	</object>
	<object>
		<name>character</name>
		<pose>Unspecified</pose>
		<truncated>0</truncated>
		<difficult>0</difficult>
		<bndbox>
			<xmin>1700</xmin>
			<ymin>1207</ymin>
			<xmax>1864</xmax>
			<ymax>1333</ymax>
		</bndbox>
	</object>
</annotation>